pac0/cli/__init__.py
pac0/cli/command/console/app.py
pac0/cli/command/console/screens/services.py
pac0/cli/command/console/screens/stats.py
pac0/cli/command/console/screens/tests.py
pac0/cli/command/console/services/__init__.py
pac0/cli/command/console/widgets/__init__.py
pac0/cli/command/run.py
pac0/cli/command/setup.py
pac0/cli/command/test.py
pac0/cli/lib/setup.py
pac0/cli/main.py
pac0/cli/utils.py
pac0_cli-0.12.0.dist-info/WHEEL
pac0_cli-0.12.0.dist-info/entry_points.txt
pac0_cli-0.12.0.dist-info/METADATA
pac0_cli-0.12.0.dist-info/RECORD
