Metadata-Version: 2.3
Name: pac0-cli
Version: 0.12.0
Summary: Outil en ligne de commande (CLI) du projet PAC
Author: Philippe ENTZMANN
Author-email: Philippe ENTZMANN <philippe@entzmann.name>
Requires-Dist: typer>=0.9.0
Requires-Dist: textual>=0.70.0
Requires-Dist: pyyaml>=6.0
Requires-Dist: packaging>=25.0
Requires-Python: >=3.13
